bvhio/__init__.py
bvhio/lib/Parser.py
bvhio/lib/bvh/BvhContainer.py
bvhio/lib/bvh/BvhJoint.py
bvhio/lib/bvh/__init__.py
bvhio/lib/hierarchy/Joint.py
bvhio/lib/hierarchy/__init__.py
bvhio/tests/__init__.py
bvhio/tests/test_bvh.py
bvhio/tests/test_hierarchy.py
bvhio/tests/test_io.py
bvhio/tests/utils.py
bvhio-1.5.4.dist-info/METADATA
bvhio-1.5.4.dist-info/WHEEL
bvhio-1.5.4.dist-info/licenses/LICENSE
bvhio-1.5.4.dist-info/RECORD
