Metadata-Version: 2.4
Name: bvhio
Version: 1.5.4
Summary: Read, write, edit and create .bvh files with hierarchical 3D transforms.
Project-URL: Homepage, https://github.com/Wasserwecken/bvhio
Project-URL: Bug Tracker, https://github.com/Wasserwecken/bvhio/issues
Author-email: Wasserwecken <author@example.com>
License-File: LICENSE
Classifier: License :: OSI Approved :: MIT License
Classifier: Operating System :: OS Independent
Classifier: Programming Language :: Python :: 3
Requires-Python: >=3.9
Requires-Dist: numpy
Requires-Dist: pyglm==2.8.2
Requires-Dist: spatial-transform==1.3.3
